dspy/__init__.py
dspy/__metadata__.py
dspy/adapters/__init__.py
dspy/adapters/base.py
dspy/adapters/chat_adapter.py
dspy/adapters/image_utils.py
dspy/adapters/json_adapter.py
dspy/adapters/utils.py
dspy/clients/__init__.py
dspy/clients/anyscale.py
dspy/clients/base_lm.py
dspy/clients/databricks.py
dspy/clients/embedding.py
dspy/clients/lm.py
dspy/clients/openai.py
dspy/clients/provider.py
dspy/clients/utils_finetune.py
dspy/datasets/__init__.py
dspy/datasets/colors.py
dspy/datasets/dataloader.py
dspy/datasets/dataset.py
dspy/datasets/gsm8k.py
dspy/datasets/hotpotqa.py
dspy/datasets/math.py
dspy/dsp/__init__.py
dspy/dsp/cache_utils.py
dspy/dsp/colbertv2.py
dspy/dsp/utils/__init__.py
dspy/dsp/utils/dpr.py
dspy/dsp/utils/metrics.py
dspy/dsp/utils/settings.py
dspy/dsp/utils/utils.py
dspy/evaluate/__init__.py
dspy/evaluate/auto_evaluation.py
dspy/evaluate/evaluate.py
dspy/evaluate/metrics.py
dspy/experimental/__init__.py
dspy/experimental/module_graph.py
dspy/experimental/synthetic_data.py
dspy/experimental/synthesizer/__init__.py
dspy/experimental/synthesizer/config.py
dspy/experimental/synthesizer/instruction_suffixes.py
dspy/experimental/synthesizer/signatures.py
dspy/experimental/synthesizer/synthesizer.py
dspy/experimental/synthesizer/utils.py
dspy/predict/__init__.py
dspy/predict/aggregation.py
dspy/predict/chain_of_thought.py
dspy/predict/chain_of_thought_with_hint.py
dspy/predict/knn.py
dspy/predict/langchain.py
dspy/predict/llamaindex.py
dspy/predict/multi_chain_comparison.py
dspy/predict/parallel.py
dspy/predict/parameter.py
dspy/predict/predict.py
dspy/predict/program_of_thought.py
dspy/predict/react.py
dspy/predict/retry.py
dspy/predict/avatar/__init__.py
dspy/predict/avatar/avatar.py
dspy/predict/avatar/models.py
dspy/predict/avatar/signatures.py
dspy/primitives/__init__.py
dspy/primitives/assertions.py
dspy/primitives/example.py
dspy/primitives/module.py
dspy/primitives/prediction.py
dspy/primitives/program.py
dspy/primitives/python_interpreter.py
dspy_ai_hmoazam-5.11.44.dist-info/LICENSE
dspy_ai_hmoazam-5.11.44.dist-info/METADATA
dspy_ai_hmoazam-5.11.44.dist-info/WHEEL
dspy_ai_hmoazam-5.11.44.dist-info/top_level.txt
dspy_ai_hmoazam-5.11.44.dist-info/RECORD
