Metadata-Version: 2.1
Name: dspy-ai-hmoazam
Version: 5.11.44
Summary: DSPy
Home-page: https://github.com/stanfordnlp/dsp
Author: Omar Khattab
Author-email: okhattab@stanford.edu
License: MIT License
Requires-Python: >=3.9
License-File: LICENSE
Requires-Dist: dspy>=2.5.3
